document_verifier_Silent_Canary/__init__.py
document_verifier_Silent_Canary/best.pt
document_verifier_Silent_Canary/best2.pt
document_verifier_Silent_Canary/best_back.pt
document_verifier_Silent_Canary/face_match.py
document_verifier_Silent_Canary/model.pt
document_verifier_Silent_Canary/ocr_text.py
document_verifier_Silent_Canary/qr.py
document_verifier_Silent_Canary/utils.py
document_verifier_Silent_Canary/verifier.py
document_verifier_Silent_Canary/WeChat/detect.caffemodel
document_verifier_Silent_Canary/WeChat/detect.prototxt
document_verifier_Silent_Canary/WeChat/sr.caffemodel
document_verifier_Silent_Canary/WeChat/sr.prototxt
document_verifier_Silent_Canary/models/realesr-animevideov3-x2.bin
document_verifier_Silent_Canary/models/realesr-animevideov3-x2.param
document_verifier_Silent_Canary/models/realesr-animevideov3-x3.bin
document_verifier_Silent_Canary/models/realesr-animevideov3-x3.param
document_verifier_Silent_Canary/models/realesr-animevideov3-x4.bin
document_verifier_Silent_Canary/models/realesr-animevideov3-x4.param
document_verifier_Silent_Canary/models/realesrgan-x4plus-anime.bin
document_verifier_Silent_Canary/models/realesrgan-x4plus-anime.param
document_verifier_Silent_Canary/models/realesrgan-x4plus.bin
document_verifier_Silent_Canary/models/realesrgan-x4plus.param
document_verifier_Silent_Canary/realesrgan/README_windows.md
document_verifier_Silent_Canary/realesrgan/realesrgan-ncnn-vulkan.exe
document_verifier_Silent_Canary/realesrgan/vcomp140.dll
document_verifier_Silent_Canary/realesrgan/vcomp140d.dll
civic2verifierrr-0.2.12.dist-info/METADATA
civic2verifierrr-0.2.12.dist-info/WHEEL
civic2verifierrr-0.2.12.dist-info/top_level.txt
civic2verifierrr-0.2.12.dist-info/RECORD
