Metadata-Version: 2.4
Name: civic2Verifierrr
Version: 0.2.12
Summary: Document verification package
Author: Advitiya Prakash
Author-email: advitiyaprakash08@gmail.com
Requires-Python: >=3.6
Requires-Dist: opencv-python
Requires-Dist: numpy
Requires-Dist: pillow
Requires-Dist: pytesseract
Requires-Dist: face_recognition
Requires-Dist: scikit-image
Requires-Dist: cmake
Requires-Dist: dlib
Requires-Dist: ultralytics==8.3.111
Requires-Dist: scipy
Requires-Dist: opencv-contrib-python
Dynamic: author
Dynamic: author-email
Dynamic: requires-dist
Dynamic: requires-python
Dynamic: summary
